datature_hub/__init__.py
datature_hub/hub.py
datature_hub/utils/__init__.py
datature_hub/utils/color_switch.py
datature_hub/utils/get_height_width.py
datature_hub/utils/visualize.py
datature_hub-0.2.3.dist-info/LICENSE
datature_hub-0.2.3.dist-info/METADATA
datature_hub-0.2.3.dist-info/WHEEL
datature_hub-0.2.3.dist-info/top_level.txt
datature_hub-0.2.3.dist-info/RECORD
