Metadata-Version: 2.1
Name: datature-hub
Version: 0.2.3
Summary: Loader for models trained on the Datature platform
Home-page: https://github.com/datature/hub
Author: Ian Duncan
Author-email: ian@datature.io
Classifier: Programming Language :: Python :: 3
Classifier: License :: OSI Approved :: MIT License
Classifier: Operating System :: OS Independent
Classifier: Intended Audience :: Science/Research
Requires-Python: >=3.6, <3.11
License-File: LICENSE
Requires-Dist: tensorflow (>=2.3.0)
Requires-Dist: requests (>=2.25.1)
Requires-Dist: opencv-python (>=4.5.1.48)
Requires-Dist: numpy
Requires-Dist: Pillow (>=8.2)
